{"meta":{"app":"Scuti Extractor","format":"RGBA8888","image":"sunsetcafe_c20_logsteppingstones.png","scale":"1.0","size":{"w":143,"h":105},"version":"1.0"},"frames":{"sunsetcafe_c20_logsteppingstones_64_b_0_1":{"frame":{"x":0,"y":0,"w":47,"h":41},"sourceSize":{"w":47,"h":41},"spriteSourceSize":{"x":-24,"y":-22,"w":47,"h":41},"rotated":false,"trimmed":true,"flipH":false},"sunsetcafe_c20_logsteppingstones_64_b_0_3":{"frame":{"x":47,"y":0,"w":49,"h":37},"sourceSize":{"w":49,"h":37},"spriteSourceSize":{"x":-28,"y":-23,"w":49,"h":37},"rotated":false,"trimmed":true,"flipH":false},"sunsetcafe_c20_logsteppingstones_64_b_0_0":{"frame":{"x":0,"y":41,"w":50,"h":34},"sourceSize":{"w":50,"h":34},"spriteSourceSize":{"x":-26,"y":-21,"w":50,"h":34},"rotated":false,"trimmed":true,"flipH":false},"sunsetcafe_c20_logsteppingstones_64_a_0_1":{"frame":{"x":96,"y":0,"w":47,"h":35},"sourceSize":{"w":47,"h":35},"spriteSourceSize":{"x":-24,"y":-15,"w":47,"h":35},"rotated":false,"trimmed":true,"flipH":false},"sunsetcafe_c20_logsteppingstones_64_a_0_0":{"frame":{"x":0,"y":75,"w":50,"h":30},"sourceSize":{"w":50,"h":30},"spriteSourceSize":{"x":-26,"y":-16,"w":50,"h":30},"rotated":false,"trimmed":true,"flipH":false},"sunsetcafe_c20_logsteppingstones_64_a_0_3":{"frame":{"x":50,"y":75,"w":49,"h":30},"sourceSize":{"w":49,"h":30},"spriteSourceSize":{"x":-28,"y":-15,"w":49,"h":30},"rotated":false,"trimmed":true,"flipH":false},"sunsetcafe_c20_logsteppingstones_64_b_0_2":{"frame":{"x":96,"y":35,"w":42,"h":28},"sourceSize":{"w":42,"h":28},"spriteSourceSize":{"x":-19,"y":-16,"w":42,"h":28},"rotated":false,"trimmed":true,"flipH":false},"sunsetcafe_c20_logsteppingstones_64_a_0_2":{"frame":{"x":50,"y":41,"w":42,"h":23},"sourceSize":{"w":42,"h":23},"spriteSourceSize":{"x":-19,"y":-10,"w":42,"h":23},"rotated":false,"trimmed":true,"flipH":false},"sunsetcafe_c20_logsteppingstones_icon_a":{"frame":{"x":99,"y":75,"w":29,"h":20},"sourceSize":{"w":29,"h":20},"spriteSourceSize":{"x":-13,"y":-7,"w":29,"h":20},"rotated":false,"trimmed":true,"flipH":false},"sunsetcafe_c20_logsteppingstones_64_a_2_0":{"frame":{"x":0,"y":75,"w":50,"h":30},"sourceSize":{"w":50,"h":30},"spriteSourceSize":{"x":-26,"y":-16,"w":50,"h":30},"rotated":false,"trimmed":true,"flipH":true},"sunsetcafe_c20_logsteppingstones_64_b_2_0":{"frame":{"x":0,"y":41,"w":50,"h":34},"sourceSize":{"w":50,"h":34},"spriteSourceSize":{"x":-26,"y":-21,"w":50,"h":34},"rotated":false,"trimmed":true,"flipH":true},"sunsetcafe_c20_logsteppingstones_64_a_2_1":{"frame":{"x":96,"y":0,"w":47,"h":35},"sourceSize":{"w":47,"h":35},"spriteSourceSize":{"x":-24,"y":-15,"w":47,"h":35},"rotated":false,"trimmed":true,"flipH":true},"sunsetcafe_c20_logsteppingstones_64_b_2_1":{"frame":{"x":0,"y":0,"w":47,"h":41},"sourceSize":{"w":47,"h":41},"spriteSourceSize":{"x":-24,"y":-22,"w":47,"h":41},"rotated":false,"trimmed":true,"flipH":true},"sunsetcafe_c20_logsteppingstones_64_a_2_2":{"frame":{"x":50,"y":41,"w":42,"h":23},"sourceSize":{"w":42,"h":23},"spriteSourceSize":{"x":-19,"y":-10,"w":42,"h":23},"rotated":false,"trimmed":true,"flipH":true},"sunsetcafe_c20_logsteppingstones_64_b_2_2":{"frame":{"x":96,"y":35,"w":42,"h":28},"sourceSize":{"w":42,"h":28},"spriteSourceSize":{"x":-19,"y":-16,"w":42,"h":28},"rotated":false,"trimmed":true,"flipH":true},"sunsetcafe_c20_logsteppingstones_64_a_2_3":{"frame":{"x":50,"y":75,"w":49,"h":30},"sourceSize":{"w":49,"h":30},"spriteSourceSize":{"x":-28,"y":-15,"w":49,"h":30},"rotated":false,"trimmed":true,"flipH":true},"sunsetcafe_c20_logsteppingstones_64_b_2_3":{"frame":{"x":47,"y":0,"w":49,"h":37},"sourceSize":{"w":49,"h":37},"spriteSourceSize":{"x":-28,"y":-23,"w":49,"h":37},"rotated":false,"trimmed":true,"flipH":true}},"furniProperty":{"infos":{"logic":"furniture_multistate","visualization":"furniture_animated"},"dimensions":{"x":null,"y":null},"visualization":{"layerCount":2,"layers":{"0":{"id":0,"z":"-2000","ignoreMouse":false},"1":{"id":1,"z":"-2000","ignoreMouse":false}},"directions":[0,2],"colors":{},"animation":{"1":{"0":{"frameSequence":[1]},"1":{"frameSequence":[1]}},"2":{"0":{"frameSequence":[2]},"1":{"frameSequence":[2]}},"3":{"0":{"frameSequence":[3]},"1":{"frameSequence":[3]}}}}}}