{"meta":{"app":"Ducket Atlas","format":"RGBA8888","image":"penguin_icehockey.png","scale":"1.0","sizes":["64","32"],"directions":[2,4],"animations":[0],"colors":[],"size":{"w":248,"h":203},"version":"1.0"},"frames":{"penguin_icehockey_64_a_4_7":{"frame":{"x":0,"y":0,"w":48,"h":91},"sourceSize":{"w":48,"h":91},"spriteSourceSize":{"x":-28,"y":-81,"w":48,"h":91},"rotated":false,"trimmed":true,"flipH":false},"penguin_icehockey_64_a_4_6":{"frame":{"x":48,"y":0,"w":50,"h":80},"sourceSize":{"w":50,"h":80},"spriteSourceSize":{"x":-30,"y":-70,"w":50,"h":80},"rotated":false,"trimmed":true,"flipH":false},"penguin_icehockey_64_a_4_2":{"frame":{"x":98,"y":0,"w":50,"h":74},"sourceSize":{"w":50,"h":74},"spriteSourceSize":{"x":-30,"y":-64,"w":50,"h":74},"rotated":false,"trimmed":true,"flipH":false},"penguin_icehockey_64_a_4_0":{"frame":{"x":148,"y":0,"w":50,"h":73},"sourceSize":{"w":50,"h":73},"spriteSourceSize":{"x":-30,"y":-63,"w":50,"h":73},"rotated":false,"trimmed":true,"flipH":false},"penguin_icehockey_64_a_4_1":{"frame":{"x":0,"y":91,"w":50,"h":73},"sourceSize":{"w":50,"h":73},"spriteSourceSize":{"x":-30,"y":-63,"w":50,"h":73},"rotated":false,"trimmed":true,"flipH":false},"penguin_icehockey_64_a_4_3":{"frame":{"x":50,"y":91,"w":50,"h":73},"sourceSize":{"w":50,"h":73},"spriteSourceSize":{"x":-30,"y":-63,"w":50,"h":73},"rotated":false,"trimmed":true,"flipH":false},"penguin_icehockey_64_a_4_4":{"frame":{"x":100,"y":91,"w":50,"h":73},"sourceSize":{"w":50,"h":73},"spriteSourceSize":{"x":-30,"y":-63,"w":50,"h":73},"rotated":false,"trimmed":true,"flipH":false},"penguin_icehockey_64_a_4_5":{"frame":{"x":198,"y":0,"w":50,"h":73},"sourceSize":{"w":50,"h":73},"spriteSourceSize":{"x":-30,"y":-63,"w":50,"h":73},"rotated":false,"trimmed":true,"flipH":false},"penguin_icehockey_32_a_4_7":{"frame":{"x":198,"y":73,"w":26,"h":47},"sourceSize":{"w":26,"h":47},"spriteSourceSize":{"x":-13,"y":-41,"w":26,"h":47},"rotated":false,"trimmed":true,"flipH":false},"penguin_icehockey_32_a_4_6":{"frame":{"x":198,"y":120,"w":28,"h":41},"sourceSize":{"w":28,"h":41},"spriteSourceSize":{"x":-15,"y":-35,"w":28,"h":41},"rotated":false,"trimmed":true,"flipH":false},"penguin_icehockey_32_a_4_0":{"frame":{"x":150,"y":91,"w":28,"h":39},"sourceSize":{"w":28,"h":39},"spriteSourceSize":{"x":-15,"y":-33,"w":28,"h":39},"rotated":false,"trimmed":true,"flipH":false},"penguin_icehockey_32_a_4_1":{"frame":{"x":0,"y":164,"w":28,"h":39},"sourceSize":{"w":28,"h":39},"spriteSourceSize":{"x":-15,"y":-33,"w":28,"h":39},"rotated":false,"trimmed":true,"flipH":false},"penguin_icehockey_32_a_4_2":{"frame":{"x":28,"y":164,"w":28,"h":39},"sourceSize":{"w":28,"h":39},"spriteSourceSize":{"x":-15,"y":-33,"w":28,"h":39},"rotated":false,"trimmed":true,"flipH":false},"penguin_icehockey_32_a_4_3":{"frame":{"x":56,"y":164,"w":28,"h":39},"sourceSize":{"w":28,"h":39},"spriteSourceSize":{"x":-15,"y":-33,"w":28,"h":39},"rotated":false,"trimmed":true,"flipH":false},"penguin_icehockey_32_a_4_4":{"frame":{"x":84,"y":164,"w":28,"h":39},"sourceSize":{"w":28,"h":39},"spriteSourceSize":{"x":-15,"y":-33,"w":28,"h":39},"rotated":false,"trimmed":true,"flipH":false},"penguin_icehockey_32_a_4_5":{"frame":{"x":112,"y":164,"w":28,"h":39},"sourceSize":{"w":28,"h":39},"spriteSourceSize":{"x":-15,"y":-33,"w":28,"h":39},"rotated":false,"trimmed":true,"flipH":false},"penguin_icehockey_64_sd_4_0":{"frame":{"x":148,"y":73,"w":47,"h":17},"sourceSize":{"w":47,"h":17},"spriteSourceSize":{"x":-29,"y":-6,"w":47,"h":17},"rotated":false,"trimmed":true,"flipH":false},"penguin_icehockey_icon_a":{"frame":{"x":224,"y":73,"w":22,"h":30},"sourceSize":{"w":22,"h":30},"spriteSourceSize":{"x":-11,"y":-15,"w":22,"h":30},"rotated":false,"trimmed":true,"flipH":false},"penguin_icehockey_32_sd_4_0":{"frame":{"x":98,"y":74,"w":26,"h":10},"sourceSize":{"w":26,"h":10},"spriteSourceSize":{"x":-14,"y":-3,"w":26,"h":10},"rotated":false,"trimmed":true,"flipH":false},"penguin_icehockey_64_a_2_0":{"frame":{"x":148,"y":0,"w":50,"h":73},"sourceSize":{"w":50,"h":73},"spriteSourceSize":{"x":-30,"y":-63,"w":50,"h":73},"rotated":false,"trimmed":true,"flipH":true},"penguin_icehockey_64_a_2_1":{"frame":{"x":0,"y":91,"w":50,"h":73},"sourceSize":{"w":50,"h":73},"spriteSourceSize":{"x":-30,"y":-63,"w":50,"h":73},"rotated":false,"trimmed":true,"flipH":true},"penguin_icehockey_64_a_2_2":{"frame":{"x":98,"y":0,"w":50,"h":74},"sourceSize":{"w":50,"h":74},"spriteSourceSize":{"x":-30,"y":-64,"w":50,"h":74},"rotated":false,"trimmed":true,"flipH":true},"penguin_icehockey_64_a_2_3":{"frame":{"x":50,"y":91,"w":50,"h":73},"sourceSize":{"w":50,"h":73},"spriteSourceSize":{"x":-30,"y":-63,"w":50,"h":73},"rotated":false,"trimmed":true,"flipH":true},"penguin_icehockey_64_a_2_4":{"frame":{"x":100,"y":91,"w":50,"h":73},"sourceSize":{"w":50,"h":73},"spriteSourceSize":{"x":-30,"y":-63,"w":50,"h":73},"rotated":false,"trimmed":true,"flipH":true},"penguin_icehockey_64_a_2_5":{"frame":{"x":198,"y":0,"w":50,"h":73},"sourceSize":{"w":50,"h":73},"spriteSourceSize":{"x":-30,"y":-63,"w":50,"h":73},"rotated":false,"trimmed":true,"flipH":true},"penguin_icehockey_64_a_2_6":{"frame":{"x":48,"y":0,"w":50,"h":80},"sourceSize":{"w":50,"h":80},"spriteSourceSize":{"x":-30,"y":-70,"w":50,"h":80},"rotated":false,"trimmed":true,"flipH":true},"penguin_icehockey_64_a_2_7":{"frame":{"x":0,"y":0,"w":48,"h":91},"sourceSize":{"w":48,"h":91},"spriteSourceSize":{"x":-28,"y":-81,"w":48,"h":91},"rotated":false,"trimmed":true,"flipH":true},"penguin_icehockey_64_sd_2_0":{"frame":{"x":148,"y":73,"w":47,"h":17},"sourceSize":{"w":47,"h":17},"spriteSourceSize":{"x":-29,"y":-6,"w":47,"h":17},"rotated":false,"trimmed":true,"flipH":true},"penguin_icehockey_32_a_2_0":{"frame":{"x":150,"y":91,"w":28,"h":39},"sourceSize":{"w":28,"h":39},"spriteSourceSize":{"x":-15,"y":-33,"w":28,"h":39},"rotated":false,"trimmed":true,"flipH":true},"penguin_icehockey_32_a_2_1":{"frame":{"x":0,"y":164,"w":28,"h":39},"sourceSize":{"w":28,"h":39},"spriteSourceSize":{"x":-15,"y":-33,"w":28,"h":39},"rotated":false,"trimmed":true,"flipH":true},"penguin_icehockey_32_a_2_2":{"frame":{"x":28,"y":164,"w":28,"h":39},"sourceSize":{"w":28,"h":39},"spriteSourceSize":{"x":-15,"y":-33,"w":28,"h":39},"rotated":false,"trimmed":true,"flipH":true},"penguin_icehockey_32_a_2_3":{"frame":{"x":56,"y":164,"w":28,"h":39},"sourceSize":{"w":28,"h":39},"spriteSourceSize":{"x":-15,"y":-33,"w":28,"h":39},"rotated":false,"trimmed":true,"flipH":true},"penguin_icehockey_32_a_2_4":{"frame":{"x":84,"y":164,"w":28,"h":39},"sourceSize":{"w":28,"h":39},"spriteSourceSize":{"x":-15,"y":-33,"w":28,"h":39},"rotated":false,"trimmed":true,"flipH":true},"penguin_icehockey_32_a_2_5":{"frame":{"x":112,"y":164,"w":28,"h":39},"sourceSize":{"w":28,"h":39},"spriteSourceSize":{"x":-15,"y":-33,"w":28,"h":39},"rotated":false,"trimmed":true,"flipH":true},"penguin_icehockey_32_a_2_6":{"frame":{"x":198,"y":120,"w":28,"h":41},"sourceSize":{"w":28,"h":41},"spriteSourceSize":{"x":-15,"y":-35,"w":28,"h":41},"rotated":false,"trimmed":true,"flipH":true},"penguin_icehockey_32_a_2_7":{"frame":{"x":198,"y":73,"w":26,"h":47},"sourceSize":{"w":26,"h":47},"spriteSourceSize":{"x":-13,"y":-41,"w":26,"h":47},"rotated":false,"trimmed":true,"flipH":true},"penguin_icehockey_32_sd_2_0":{"frame":{"x":98,"y":74,"w":26,"h":10},"sourceSize":{"w":26,"h":10},"spriteSourceSize":{"x":-14,"y":-3,"w":26,"h":10},"rotated":false,"trimmed":true,"flipH":true}},"furniProperty":{"infos":{"logic":"furniture_multistate","visualization":"furniture_animated"},"dimensions":{"x":null,"y":null},"visualization":{"layerCount":1,"layers":{},"directions":[2,4],"colors":{},"animation":{"0":{"0":{"frameSequence":[0,0,0,0,0,0,0,0,0,0,0,0,0,0,0,0,0,0,0,0,0,0,0,0,0,0,0,0,0,0,0,0,0,0,0,0,0,0,0,0,0,0,0,0,0,0,0,0,0,1,0,0,0,0,0,0,0,0,0,0,0,0,0,0,0,0,0,0,0,0,0,0,0,0,0,0,0,0,0,0,0,0,0,0,0,0,0,0,0,0,0,0,0,0,0,0,0,0,0,0,0,0,1,0,0,0,0,0,0,0,0,0,0,0,0,0,0,0,0,0,0,0,0,0,0,0,0,0,0,0,0,0,0,0,0,0,0,0,0,0,0,0,0,0,0,0,0,0,0,0,0,1,0,0,0,0,0,0,0,0,0,0,0,0,0,0,0,0,0,0,0,0,0,0,0,0,0,0,0,0,0,0,0,0,0,0,0,0,0,0,0,0,0,0,0,0,0,0,0,0,0,0,0,0,0,0,0,1,0,0,0,0,0,0,0,0,0,0,0,0,0,0,0,0,0,0,0,0,0,0,0,0,0,0,0,0,0,0,0,0,0,0,0,0,0,0,0,0,0,0,0,0,0,0,0,0,0,0,0,0,0,0,0,0,0,0,1,0,0,0,0,0,0,0,0,0,0,0,0,0,0,0,0,0,0,0,0,0,0,0,0,0,0,0,0,0,0,0,0,0,0,0,0,0,0,0,0,0,0,0,0,0,0,0,0,0,1,0,0,0,0,0,0,0,0,0,0,0,0,0,0,0,0,0,0,0,0,0,0,0,0,0,0,0,0,0,0,0,0,0,0,0,0,0,0,0,0,0,0,0,0,0,0,0,0,0,0,0,0,0,0,1,0,0,0,0,0,0,0,0,0,0,0,0,0,0,0,0,0,0,0,0,0,0,0,0,0,0,0,0,0,0,0,0,0,0,0,0,0,0,0,0,0,0,0,0,0,0,0,0,0,0,0,0,0,0,0,0,0,0,0,0,1,0,0,0,0,0,0,0,0,0,0,0,0,0,0,0,0,0,0,0,0,0,0,0,0,0,0,0,0,0,0,0,0,0,0,0,0,0,0,0,0,0,0,0,0,0,0,0,1,0,0,0,0,0,0,0,0,0,0,0,0,0,0,0,0,0,0,0,0,0,0,0,0,0,0,0,0,0,0,6,7,7,7,7,7,7,6,6,6,7,7,7,7,6,6,6,7,7,7,7,6,0,0,0,0,0,0,0,0,0,0,1,0,0,0,0,0,0,0,0,0,0,0,0,0,0,0,0,0,0,0,0,0,0,0,0,0,0,0,0,0,0,0,0,0,4,4,0,0,5,5,0,0,4,4,0,0,5,5,0,0,4,4,0,0,5,5,0,0,0,0,0,0,1,0,0,0,0,0,0,0,0,0,0,0,0,0,0,0,0,0,0,0,0,0,0,0,0,0,0,0,0,0,0,0,0,0,0,2,2,2,2,2,2,2,2,2,2,2,2,2,2,0,0,0,0,0,0,1,0,0,0,0,0,0,0,0,0,0,0,0,0,0,0,0,0,0,0,0,0,0,0,0,0,0,0,0,3,3,3,3,0,0,0,0,3,3,0,0,3,3,0,0,1,0,0,0,0,0,0,0,0,0,0,0,0,0,0,0,0,0,0,0,0,0,0,0,0,0,0,0,0,1,1,1,0,0,0,0,0,0,1,1,1,1,1,1,0,0,0,0,0,0,0,0,0,1,1,1,1,1,1,1,1,1,1,1,1,1,1,1,1,1,1,1,1,1,1,1,1,1,1,1,1,1,1,1,1,1,1,1,1,1,1,1,1,1,1,1,1,1,0,0,0,0,0,0,1,1,1,1,1,1,0,0,0,0,0,0,1,0,0,0,0,0,0,0,0,0,0,0,0,0,0,0,0,0,0,0,0,0,0,0,0,0,0,0,0,0,0,0,0,4,5,4,5,4,5,4,5,4,5,0,0,0,0,0,0,0,1],"loopCount":0,"random":1,"frameRepeat":4}}}}}}