{"meta":{"app":"Scuti Extractor","format":"RGBA8888","image":"samovar.png","scale":"1.0","size":{"w":119,"h":79},"version":"1.0"},"frames":{"samovar_64_a_2_0":{"frame":{"x":0,"y":0,"w":55,"h":79},"sourceSize":{"w":55,"h":79},"spriteSourceSize":{"x":-28,"y":-69,"w":55,"h":79},"rotated":false,"trimmed":true,"flipH":false},"samovar_32_a_2_0":{"frame":{"x":55,"y":0,"w":28,"h":40},"sourceSize":{"w":28,"h":40},"spriteSourceSize":{"x":-15,"y":-34,"w":28,"h":40},"rotated":false,"trimmed":true,"flipH":false},"samovar_icon_a":{"frame":{"x":55,"y":40,"w":24,"h":30},"sourceSize":{"w":24,"h":30},"spriteSourceSize":{"x":-12,"y":-15,"w":24,"h":30},"rotated":false,"trimmed":true,"flipH":false},"samovar_64_sd_0_0":{"frame":{"x":83,"y":0,"w":36,"h":19},"sourceSize":{"w":36,"h":19},"spriteSourceSize":{"x":-17,"y":-9,"w":36,"h":19},"rotated":false,"trimmed":true,"flipH":false},"samovar_32_sd_0_0":{"frame":{"x":83,"y":19,"w":18,"h":9},"sourceSize":{"w":18,"h":9},"spriteSourceSize":{"x":-9,"y":-2,"w":18,"h":9},"rotated":false,"trimmed":true,"flipH":false},"samovar_32_a_4_0":{"frame":{"x":55,"y":0,"w":28,"h":40},"sourceSize":{"w":28,"h":40},"spriteSourceSize":{"x":-15,"y":-34,"w":28,"h":40},"rotated":false,"trimmed":true,"flipH":true},"samovar_32_sd_2_0":{"frame":{"x":83,"y":19,"w":18,"h":9},"sourceSize":{"w":18,"h":9},"spriteSourceSize":{"x":-9,"y":-2,"w":18,"h":9},"rotated":false,"trimmed":true,"flipH":false},"samovar_32_sd_4_0":{"frame":{"x":83,"y":19,"w":18,"h":9},"sourceSize":{"w":18,"h":9},"spriteSourceSize":{"x":-9,"y":-2,"w":18,"h":9},"rotated":false,"trimmed":true,"flipH":false},"samovar_64_a_4_0":{"frame":{"x":0,"y":0,"w":55,"h":79},"sourceSize":{"w":55,"h":79},"spriteSourceSize":{"x":-28,"y":-69,"w":55,"h":79},"rotated":false,"trimmed":true,"flipH":true},"samovar_64_sd_2_0":{"frame":{"x":83,"y":0,"w":36,"h":19},"sourceSize":{"w":36,"h":19},"spriteSourceSize":{"x":-17,"y":-9,"w":36,"h":19},"rotated":false,"trimmed":true,"flipH":false},"samovar_64_sd_4_0":{"frame":{"x":83,"y":0,"w":36,"h":19},"sourceSize":{"w":36,"h":19},"spriteSourceSize":{"x":-17,"y":-9,"w":36,"h":19},"rotated":false,"trimmed":true,"flipH":false}},"furniProperty":{"infos":{"logic":"furniture_multistate","visualization":"furniture_static"},"dimensions":{"x":null,"y":null},"visualization":{"layerCount":1,"layers":{},"directions":[2,4],"colors":{},"animation":{}}}}