{"meta":{"app":"Ducket Atlas","format":"RGBA8888","image":"nft_diamond_painting55.png","scale":"1.0","sizes":["64"],"directions":[2,4],"animations":[],"colors":[],"size":{"w":124,"h":125},"version":"1.0"},"frames":{"nft_diamond_painting55_64_a_2_0":{"frame":{"x":0,"y":0,"w":94,"h":125},"sourceSize":{"w":94,"h":125},"spriteSourceSize":{"x":-46,"y":-66,"w":94,"h":125},"rotated":false,"trimmed":true,"flipH":false},"nft_diamond_painting55_icon_a":{"frame":{"x":94,"y":0,"w":30,"h":30},"sourceSize":{"w":30,"h":30},"spriteSourceSize":{"x":-15,"y":-15,"w":30,"h":30},"rotated":false,"trimmed":true,"flipH":false},"nft_diamond_painting55_64_a_4_0":{"frame":{"x":0,"y":0,"w":94,"h":125},"sourceSize":{"w":94,"h":125},"spriteSourceSize":{"x":-46,"y":-66,"w":94,"h":125},"rotated":false,"trimmed":true,"flipH":true}},"furniProperty":{"infos":{"logic":"furniture_basic","visualization":"furniture_static"},"dimensions":{"x":null,"y":null},"visualization":{"layerCount":1,"layers":{"0":{"id":0,"z":"-2000","ignoreMouse":false}},"directions":[2,4],"colors":{},"animation":{}}}}