{"meta":{"app":"Scuti Extractor","format":"RGBA8888","image":"xmas_c22_penguin7.png","scale":"1.0","size":{"w":203,"h":201},"version":"1.0"},"frames":{"xmas_c22_penguin7_64_a_0_0":{"frame":{"x":0,"y":0,"w":41,"h":67},"sourceSize":{"w":41,"h":67},"spriteSourceSize":{"x":-25,"y":-60,"w":41,"h":67},"rotated":false,"trimmed":true,"flipH":false},"xmas_c22_penguin7_64_a_0_1":{"frame":{"x":41,"y":0,"w":41,"h":67},"sourceSize":{"w":41,"h":67},"spriteSourceSize":{"x":-25,"y":-60,"w":41,"h":67},"rotated":false,"trimmed":true,"flipH":false},"xmas_c22_penguin7_64_a_0_8":{"frame":{"x":82,"y":0,"w":41,"h":67},"sourceSize":{"w":41,"h":67},"spriteSourceSize":{"x":-25,"y":-60,"w":41,"h":67},"rotated":false,"trimmed":true,"flipH":false},"xmas_c22_penguin7_64_a_0_10":{"frame":{"x":123,"y":0,"w":40,"h":67},"sourceSize":{"w":40,"h":67},"spriteSourceSize":{"x":-25,"y":-60,"w":40,"h":67},"rotated":false,"trimmed":true,"flipH":false},"xmas_c22_penguin7_64_a_0_11":{"frame":{"x":0,"y":67,"w":40,"h":67},"sourceSize":{"w":40,"h":67},"spriteSourceSize":{"x":-25,"y":-60,"w":40,"h":67},"rotated":false,"trimmed":true,"flipH":false},"xmas_c22_penguin7_64_a_0_12":{"frame":{"x":40,"y":67,"w":40,"h":67},"sourceSize":{"w":40,"h":67},"spriteSourceSize":{"x":-25,"y":-60,"w":40,"h":67},"rotated":false,"trimmed":true,"flipH":false},"xmas_c22_penguin7_64_a_0_2":{"frame":{"x":80,"y":67,"w":40,"h":67},"sourceSize":{"w":40,"h":67},"spriteSourceSize":{"x":-25,"y":-60,"w":40,"h":67},"rotated":false,"trimmed":true,"flipH":false},"xmas_c22_penguin7_64_a_0_3":{"frame":{"x":120,"y":67,"w":40,"h":67},"sourceSize":{"w":40,"h":67},"spriteSourceSize":{"x":-25,"y":-60,"w":40,"h":67},"rotated":false,"trimmed":true,"flipH":false},"xmas_c22_penguin7_64_a_0_4":{"frame":{"x":163,"y":0,"w":40,"h":67},"sourceSize":{"w":40,"h":67},"spriteSourceSize":{"x":-25,"y":-60,"w":40,"h":67},"rotated":false,"trimmed":true,"flipH":false},"xmas_c22_penguin7_64_a_0_5":{"frame":{"x":163,"y":67,"w":40,"h":67},"sourceSize":{"w":40,"h":67},"spriteSourceSize":{"x":-25,"y":-60,"w":40,"h":67},"rotated":false,"trimmed":true,"flipH":false},"xmas_c22_penguin7_64_a_0_6":{"frame":{"x":0,"y":134,"w":40,"h":67},"sourceSize":{"w":40,"h":67},"spriteSourceSize":{"x":-25,"y":-60,"w":40,"h":67},"rotated":false,"trimmed":true,"flipH":false},"xmas_c22_penguin7_64_a_0_7":{"frame":{"x":40,"y":134,"w":40,"h":67},"sourceSize":{"w":40,"h":67},"spriteSourceSize":{"x":-25,"y":-60,"w":40,"h":67},"rotated":false,"trimmed":true,"flipH":false},"xmas_c22_penguin7_64_a_0_9":{"frame":{"x":80,"y":134,"w":40,"h":67},"sourceSize":{"w":40,"h":67},"spriteSourceSize":{"x":-25,"y":-60,"w":40,"h":67},"rotated":false,"trimmed":true,"flipH":false},"xmas_c22_penguin7_icon_a":{"frame":{"x":120,"y":134,"w":24,"h":30},"sourceSize":{"w":24,"h":30},"spriteSourceSize":{"x":-15,"y":-15,"w":24,"h":30},"rotated":false,"trimmed":true,"flipH":false},"xmas_c22_penguin7_64_sd_0_0":{"frame":{"x":144,"y":134,"w":29,"h":16},"sourceSize":{"w":29,"h":16},"spriteSourceSize":{"x":-14,"y":-5,"w":29,"h":16},"rotated":false,"trimmed":true,"flipH":false},"xmas_c22_penguin7_64_sd_2_0":{"frame":{"x":144,"y":134,"w":29,"h":16},"sourceSize":{"w":29,"h":16},"spriteSourceSize":{"x":-14,"y":-5,"w":29,"h":16},"rotated":false,"trimmed":true,"flipH":true},"xmas_c22_penguin7_64_a_2_0":{"frame":{"x":0,"y":0,"w":41,"h":67},"sourceSize":{"w":41,"h":67},"spriteSourceSize":{"x":-25,"y":-60,"w":41,"h":67},"rotated":false,"trimmed":true,"flipH":true},"xmas_c22_penguin7_64_a_2_1":{"frame":{"x":41,"y":0,"w":41,"h":67},"sourceSize":{"w":41,"h":67},"spriteSourceSize":{"x":-25,"y":-60,"w":41,"h":67},"rotated":false,"trimmed":true,"flipH":true},"xmas_c22_penguin7_64_a_2_2":{"frame":{"x":80,"y":67,"w":40,"h":67},"sourceSize":{"w":40,"h":67},"spriteSourceSize":{"x":-25,"y":-60,"w":40,"h":67},"rotated":false,"trimmed":true,"flipH":true},"xmas_c22_penguin7_64_a_2_3":{"frame":{"x":120,"y":67,"w":40,"h":67},"sourceSize":{"w":40,"h":67},"spriteSourceSize":{"x":-25,"y":-60,"w":40,"h":67},"rotated":false,"trimmed":true,"flipH":true},"xmas_c22_penguin7_64_a_2_4":{"frame":{"x":163,"y":0,"w":40,"h":67},"sourceSize":{"w":40,"h":67},"spriteSourceSize":{"x":-25,"y":-60,"w":40,"h":67},"rotated":false,"trimmed":true,"flipH":true},"xmas_c22_penguin7_64_a_2_5":{"frame":{"x":163,"y":67,"w":40,"h":67},"sourceSize":{"w":40,"h":67},"spriteSourceSize":{"x":-25,"y":-60,"w":40,"h":67},"rotated":false,"trimmed":true,"flipH":true},"xmas_c22_penguin7_64_a_2_6":{"frame":{"x":0,"y":134,"w":40,"h":67},"sourceSize":{"w":40,"h":67},"spriteSourceSize":{"x":-25,"y":-60,"w":40,"h":67},"rotated":false,"trimmed":true,"flipH":true},"xmas_c22_penguin7_64_a_2_7":{"frame":{"x":40,"y":134,"w":40,"h":67},"sourceSize":{"w":40,"h":67},"spriteSourceSize":{"x":-25,"y":-60,"w":40,"h":67},"rotated":false,"trimmed":true,"flipH":true},"xmas_c22_penguin7_64_a_2_8":{"frame":{"x":82,"y":0,"w":41,"h":67},"sourceSize":{"w":41,"h":67},"spriteSourceSize":{"x":-25,"y":-60,"w":41,"h":67},"rotated":false,"trimmed":true,"flipH":true},"xmas_c22_penguin7_64_a_2_9":{"frame":{"x":80,"y":134,"w":40,"h":67},"sourceSize":{"w":40,"h":67},"spriteSourceSize":{"x":-25,"y":-60,"w":40,"h":67},"rotated":false,"trimmed":true,"flipH":true},"xmas_c22_penguin7_64_a_2_10":{"frame":{"x":123,"y":0,"w":40,"h":67},"sourceSize":{"w":40,"h":67},"spriteSourceSize":{"x":-25,"y":-60,"w":40,"h":67},"rotated":false,"trimmed":true,"flipH":true},"xmas_c22_penguin7_64_a_2_11":{"frame":{"x":0,"y":67,"w":40,"h":67},"sourceSize":{"w":40,"h":67},"spriteSourceSize":{"x":-25,"y":-60,"w":40,"h":67},"rotated":false,"trimmed":true,"flipH":true},"xmas_c22_penguin7_64_a_2_12":{"frame":{"x":40,"y":67,"w":40,"h":67},"sourceSize":{"w":40,"h":67},"spriteSourceSize":{"x":-25,"y":-60,"w":40,"h":67},"rotated":false,"trimmed":true,"flipH":true}},"furniProperty":{"infos":{"logic":"furniture_multistate","visualization":"furniture_animated"},"dimensions":{"x":null,"y":null},"visualization":{"layerCount":1,"layers":{},"directions":[0,2],"colors":{},"animation":{"0":{"0":{"frameSequence":[0,0,0,0,0,0,0,1,2,3,4,5,6,7,8,9,10,11,12,0,0,0,0,0,0,0,0,0,0,0,0,0,0,0,0,0,0,0,0,0,0,0,0,0,0,0,0,0,0,0,0,0,0,0,0,0,0,0,0,0,0,0,0,0,0,0,0,0,0,0,0,0,0,0,0,0,0,0,0,0,0,0,0,0,0,0,0,0,0,0,0,0,0,0,0,0,0,0,0,0,0,0,0,0,0,0,0,1,1,1,1,1,1,1,0,0,0,0,0,0,0,0,1,1,1,1,1,1,1,1,1,1,1,1,1,1,1,1,1,1,1,1,1,1,0],"loopCount":0,"random":1,"frameRepeat":3}}}}}}