{"meta":{"app":"Scuti Extractor","format":"RGBA8888","image":"xm09_bauble_25.png","scale":"1.0","size":{"w":54,"h":47},"version":"1.0"},"frames":{"xm09_bauble_25_64_b_2_0":{"frame":{"x":0,"y":0,"w":18,"h":31},"sourceSize":{"w":18,"h":31},"spriteSourceSize":{"x":-9,"y":-16,"w":18,"h":31},"rotated":false,"trimmed":true,"flipH":false},"xm09_bauble_25_icon_a":{"frame":{"x":18,"y":0,"w":18,"h":30},"sourceSize":{"w":18,"h":30},"spriteSourceSize":{"x":-9,"y":-15,"w":18,"h":30},"rotated":false,"trimmed":true,"flipH":false},"xm09_bauble_25_64_a_2_0":{"frame":{"x":36,"y":0,"w":18,"h":22},"sourceSize":{"w":18,"h":22},"spriteSourceSize":{"x":-10,"y":-6,"w":18,"h":22},"rotated":false,"trimmed":true,"flipH":false},"xm09_bauble_25_32_b_2_0":{"frame":{"x":0,"y":31,"w":11,"h":16},"sourceSize":{"w":11,"h":16},"spriteSourceSize":{"x":-5,"y":-9,"w":11,"h":16},"rotated":false,"trimmed":true,"flipH":false},"xm09_bauble_25_32_a_2_0":{"frame":{"x":11,"y":31,"w":11,"h":12},"sourceSize":{"w":11,"h":12},"spriteSourceSize":{"x":-6,"y":-4,"w":11,"h":12},"rotated":false,"trimmed":true,"flipH":false},"xm09_bauble_25_64_a_4_0":{"frame":{"x":36,"y":0,"w":18,"h":22},"sourceSize":{"w":18,"h":22},"spriteSourceSize":{"x":-10,"y":-6,"w":18,"h":22},"rotated":false,"trimmed":true,"flipH":true},"xm09_bauble_25_64_b_4_0":{"frame":{"x":0,"y":0,"w":18,"h":31},"sourceSize":{"w":18,"h":31},"spriteSourceSize":{"x":-9,"y":-16,"w":18,"h":31},"rotated":false,"trimmed":true,"flipH":true},"xm09_bauble_25_32_a_4_0":{"frame":{"x":11,"y":31,"w":11,"h":12},"sourceSize":{"w":11,"h":12},"spriteSourceSize":{"x":-6,"y":-4,"w":11,"h":12},"rotated":false,"trimmed":true,"flipH":true},"xm09_bauble_25_32_b_4_0":{"frame":{"x":0,"y":31,"w":11,"h":16},"sourceSize":{"w":11,"h":16},"spriteSourceSize":{"x":-5,"y":-9,"w":11,"h":16},"rotated":false,"trimmed":true,"flipH":true}},"furniProperty":{"infos":{"logic":"furniture_multistate","visualization":"furniture_animated"},"dimensions":{"x":null,"y":null},"visualization":{"layerCount":2,"layers":{"0":{"id":0,"alpha":41,"z":"-3000","ignoreMouse":false},"1":{"id":1,"z":"-2990","ignoreMouse":false}},"directions":[2,4],"colors":{},"animation":{"0":{"0":{"frameSequence":[0]},"1":{"frameSequence":[0]}}}}}}