{"meta":{"app":"Scuti Extractor","format":"RGBA8888","image":"nft_ff23_v7_icecream_bliss.png","scale":"1.0","size":{"w":390,"h":343},"version":"1.0"},"frames":{"nft_ff23_v7_icecream_bliss_64_b_2_1":{"frame":{"x":0,"y":0,"w":92,"h":135},"sourceSize":{"w":92,"h":135},"spriteSourceSize":{"x":0,"y":0,"w":92,"h":135},"rotated":false,"trimmed":true},"nft_ff23_v7_icecream_bliss_64_d_2_1":{"frame":{"x":92,"y":0,"w":50,"h":109},"sourceSize":{"w":50,"h":109},"spriteSourceSize":{"x":0,"y":0,"w":50,"h":109},"rotated":false,"trimmed":true},"nft_ff23_v7_icecream_bliss_64_d_2_11":{"frame":{"x":142,"y":0,"w":50,"h":109},"sourceSize":{"w":50,"h":109},"spriteSourceSize":{"x":0,"y":0,"w":50,"h":109},"rotated":false,"trimmed":true},"nft_ff23_v7_icecream_bliss_64_d_2_17":{"frame":{"x":192,"y":0,"w":49,"h":105},"sourceSize":{"w":49,"h":105},"spriteSourceSize":{"x":0,"y":0,"w":49,"h":105},"rotated":false,"trimmed":true},"nft_ff23_v7_icecream_bliss_64_d_2_7":{"frame":{"x":0,"y":135,"w":49,"h":105},"sourceSize":{"w":49,"h":105},"spriteSourceSize":{"x":0,"y":0,"w":49,"h":105},"rotated":false,"trimmed":true},"nft_ff23_v7_icecream_bliss_64_d_2_12":{"frame":{"x":49,"y":135,"w":50,"h":102},"sourceSize":{"w":50,"h":102},"spriteSourceSize":{"x":0,"y":0,"w":50,"h":102},"rotated":false,"trimmed":true},"nft_ff23_v7_icecream_bliss_64_d_2_13":{"frame":{"x":99,"y":135,"w":50,"h":102},"sourceSize":{"w":50,"h":102},"spriteSourceSize":{"x":0,"y":0,"w":50,"h":102},"rotated":false,"trimmed":true},"nft_ff23_v7_icecream_bliss_64_d_2_2":{"frame":{"x":149,"y":135,"w":50,"h":102},"sourceSize":{"w":50,"h":102},"spriteSourceSize":{"x":0,"y":0,"w":50,"h":102},"rotated":false,"trimmed":true},"nft_ff23_v7_icecream_bliss_64_d_2_3":{"frame":{"x":241,"y":0,"w":50,"h":102},"sourceSize":{"w":50,"h":102},"spriteSourceSize":{"x":0,"y":0,"w":50,"h":102},"rotated":false,"trimmed":true},"nft_ff23_v7_icecream_bliss_64_d_2_15":{"frame":{"x":241,"y":102,"w":50,"h":101},"sourceSize":{"w":50,"h":101},"spriteSourceSize":{"x":0,"y":0,"w":50,"h":101},"rotated":false,"trimmed":true},"nft_ff23_v7_icecream_bliss_64_d_2_5":{"frame":{"x":291,"y":0,"w":50,"h":101},"sourceSize":{"w":50,"h":101},"spriteSourceSize":{"x":0,"y":0,"w":50,"h":101},"rotated":false,"trimmed":true},"nft_ff23_v7_icecream_bliss_64_b_2_0":{"frame":{"x":291,"y":101,"w":49,"h":103},"sourceSize":{"w":49,"h":103},"spriteSourceSize":{"x":0,"y":0,"w":49,"h":103},"rotated":false,"trimmed":true},"nft_ff23_v7_icecream_bliss_64_d_2_14":{"frame":{"x":341,"y":0,"w":49,"h":103},"sourceSize":{"w":49,"h":103},"spriteSourceSize":{"x":0,"y":0,"w":49,"h":103},"rotated":false,"trimmed":true},"nft_ff23_v7_icecream_bliss_64_d_2_4":{"frame":{"x":341,"y":103,"w":49,"h":103},"sourceSize":{"w":49,"h":103},"spriteSourceSize":{"x":0,"y":0,"w":49,"h":103},"rotated":false,"trimmed":true},"nft_ff23_v7_icecream_bliss_64_d_2_18":{"frame":{"x":0,"y":240,"w":47,"h":103},"sourceSize":{"w":47,"h":103},"spriteSourceSize":{"x":0,"y":0,"w":47,"h":103},"rotated":false,"trimmed":true},"nft_ff23_v7_icecream_bliss_64_d_2_8":{"frame":{"x":47,"y":240,"w":47,"h":103},"sourceSize":{"w":47,"h":103},"spriteSourceSize":{"x":0,"y":0,"w":47,"h":103},"rotated":false,"trimmed":true},"nft_ff23_v7_icecream_bliss_64_d_2_19":{"frame":{"x":94,"y":240,"w":47,"h":100},"sourceSize":{"w":47,"h":100},"spriteSourceSize":{"x":0,"y":0,"w":47,"h":100},"rotated":false,"trimmed":true},"nft_ff23_v7_icecream_bliss_64_d_2_9":{"frame":{"x":141,"y":240,"w":47,"h":100},"sourceSize":{"w":47,"h":100},"spriteSourceSize":{"x":0,"y":0,"w":47,"h":100},"rotated":false,"trimmed":true},"nft_ff23_v7_icecream_bliss_64_d_2_16":{"frame":{"x":188,"y":240,"w":49,"h":95},"sourceSize":{"w":49,"h":95},"spriteSourceSize":{"x":0,"y":0,"w":49,"h":95},"rotated":false,"trimmed":true},"nft_ff23_v7_icecream_bliss_64_d_2_6":{"frame":{"x":237,"y":240,"w":49,"h":95},"sourceSize":{"w":49,"h":95},"spriteSourceSize":{"x":0,"y":0,"w":49,"h":95},"rotated":false,"trimmed":true},"nft_ff23_v7_icecream_bliss_64_d_2_10":{"frame":{"x":286,"y":240,"w":48,"h":93},"sourceSize":{"w":48,"h":93},"spriteSourceSize":{"x":0,"y":0,"w":48,"h":93},"rotated":false,"trimmed":true},"nft_ff23_v7_icecream_bliss_64_d_2_20":{"frame":{"x":334,"y":240,"w":48,"h":93},"sourceSize":{"w":48,"h":93},"spriteSourceSize":{"x":0,"y":0,"w":48,"h":93},"rotated":false,"trimmed":true},"nft_ff23_v7_icecream_bliss_64_sd_2_0":{"frame":{"x":341,"y":206,"w":43,"h":22},"sourceSize":{"w":43,"h":22},"spriteSourceSize":{"x":0,"y":0,"w":43,"h":22},"rotated":false,"trimmed":true},"nft_ff23_v7_icecream_bliss_icon_a":{"frame":{"x":291,"y":204,"w":30,"h":30},"sourceSize":{"w":30,"h":30},"spriteSourceSize":{"x":0,"y":0,"w":30,"h":30},"rotated":false,"trimmed":true},"nft_ff23_v7_icecream_bliss_64_a_2_1":{"frame":{"x":241,"y":203,"w":19,"h":31},"sourceSize":{"w":19,"h":31},"spriteSourceSize":{"x":0,"y":0,"w":19,"h":31},"rotated":false,"trimmed":true},"nft_ff23_v7_icecream_bliss_64_a_2_0":{"frame":{"x":199,"y":135,"w":7,"h":38},"sourceSize":{"w":7,"h":38},"spriteSourceSize":{"x":0,"y":0,"w":7,"h":38},"rotated":false,"trimmed":true},"nft_ff23_v7_icecream_bliss_64_d_2_0":{"frame":{"x":321,"y":204,"w":12,"h":17},"sourceSize":{"w":12,"h":17},"spriteSourceSize":{"x":0,"y":0,"w":12,"h":17},"rotated":false,"trimmed":true},"nft_ff23_v7_icecream_bliss_64_e_2_0":{"frame":{"x":260,"y":203,"w":7,"h":23},"sourceSize":{"w":7,"h":23},"spriteSourceSize":{"x":0,"y":0,"w":7,"h":23},"rotated":false,"trimmed":true}},"furniProperty":{"infos":{"logic":"furniture_multistate","visualization":"furniture_animated"},"dimensions":{"x":null,"y":null},"visualization":{"layerCount":5,"layers":{"0":{"id":0,"ignoreMouse":false},"1":{"id":1,"ignoreMouse":false},"2":{"id":2,"ignoreMouse":false},"3":{"id":3,"ignoreMouse":false}},"directions":[2,4],"colors":{},"animation":{"0":{"0":{"frameSequence":[]},"1":{"frameSequence":[0]},"2":{"frameSequence":[]},"3":{"frameSequence":[]},"4":{"frameSequence":[]}},"1":{"0":{"frameSequence":[1,1,1,1,1,1,1,1,1,1,1,1,1,1,1,1,1,1,1,1,0],"frameRepeat":4},"1":{"frameSequence":[1,1,1,1,1,1,1,1,1,1,1,1,1,1,1,1,1,1,1,1,1,1,1,1,1,1,1,1,1,1,1,1,1,1,1,1,1,1,1,0],"frameRepeat":4},"2":{"frameSequence":[]},"3":{"frameSequence":[1,2,3,4,5,6,7,8,9,10,11,12,13,14,15,16,17,18,19,20,11,12,13,14,15,16,17,18,19,20,11,12,13,14,15,16,17,18,19,20,0],"frameRepeat":4},"4":{"frameSequence":[]}}}}}}