{"meta":{"app":"Scuti Extractor","format":"RGBA8888","image":"ny2013_block.png","scale":"1.0","size":{"w":166,"h":126},"version":"1.0"},"frames":{"ny2013_block_64_a_0_0":{"frame":{"x":0,"y":0,"w":66,"h":63},"sourceSize":{"w":66,"h":63},"spriteSourceSize":{"x":-33,"y":-48,"w":66,"h":63},"rotated":false,"trimmed":true,"flipH":false},"ny2013_block_64_a_0_1":{"frame":{"x":66,"y":0,"w":66,"h":63},"sourceSize":{"w":66,"h":63},"spriteSourceSize":{"x":-33,"y":-48,"w":66,"h":63},"rotated":false,"trimmed":true,"flipH":false},"ny2013_block_64_a_0_2":{"frame":{"x":0,"y":63,"w":66,"h":63},"sourceSize":{"w":66,"h":63},"spriteSourceSize":{"x":-33,"y":-48,"w":66,"h":63},"rotated":false,"trimmed":true,"flipH":false},"ny2013_block_32_a_0_2":{"frame":{"x":66,"y":63,"w":34,"h":34},"sourceSize":{"w":34,"h":34},"spriteSourceSize":{"x":-17,"y":-25,"w":34,"h":34},"rotated":false,"trimmed":true,"flipH":false},"ny2013_block_32_a_0_0":{"frame":{"x":132,"y":0,"w":34,"h":33},"sourceSize":{"w":34,"h":33},"spriteSourceSize":{"x":-17,"y":-25,"w":34,"h":33},"rotated":false,"trimmed":true,"flipH":false},"ny2013_block_32_a_0_1":{"frame":{"x":132,"y":33,"w":34,"h":33},"sourceSize":{"w":34,"h":33},"spriteSourceSize":{"x":-17,"y":-25,"w":34,"h":33},"rotated":false,"trimmed":true,"flipH":false},"ny2013_block_icon_a":{"frame":{"x":132,"y":66,"w":28,"h":26},"sourceSize":{"w":28,"h":26},"spriteSourceSize":{"x":-13,"y":-12,"w":28,"h":26},"rotated":false,"trimmed":true,"flipH":false},"ny2013_block_32_a_2_0":{"frame":{"x":132,"y":0,"w":34,"h":33},"sourceSize":{"w":34,"h":33},"spriteSourceSize":{"x":-17,"y":-25,"w":34,"h":33},"rotated":false,"trimmed":true,"flipH":true},"ny2013_block_32_a_2_1":{"frame":{"x":132,"y":33,"w":34,"h":33},"sourceSize":{"w":34,"h":33},"spriteSourceSize":{"x":-17,"y":-25,"w":34,"h":33},"rotated":false,"trimmed":true,"flipH":true},"ny2013_block_32_a_2_2":{"frame":{"x":66,"y":63,"w":34,"h":34},"sourceSize":{"w":34,"h":34},"spriteSourceSize":{"x":-17,"y":-25,"w":34,"h":34},"rotated":false,"trimmed":true,"flipH":true},"ny2013_block_64_a_2_0":{"frame":{"x":0,"y":0,"w":66,"h":63},"sourceSize":{"w":66,"h":63},"spriteSourceSize":{"x":-33,"y":-48,"w":66,"h":63},"rotated":false,"trimmed":true,"flipH":true},"ny2013_block_64_a_2_1":{"frame":{"x":66,"y":0,"w":66,"h":63},"sourceSize":{"w":66,"h":63},"spriteSourceSize":{"x":-33,"y":-48,"w":66,"h":63},"rotated":false,"trimmed":true,"flipH":true},"ny2013_block_64_a_2_2":{"frame":{"x":0,"y":63,"w":66,"h":63},"sourceSize":{"w":66,"h":63},"spriteSourceSize":{"x":-33,"y":-48,"w":66,"h":63},"rotated":false,"trimmed":true,"flipH":true}},"furniProperty":{"infos":{"logic":"furniture_multistate","visualization":"furniture_animated"},"dimensions":{"x":null,"y":null},"visualization":{"layerCount":1,"layers":{},"directions":[0,2],"colors":{},"animation":{"0":{"0":{"frameSequence":[]}},"1":{"0":{"frameSequence":[1]}},"2":{"0":{"frameSequence":[2]}}}}}}